sibyl/__init__.py
sibyl/cli.py
sibyl/config.yml
sibyl/core.py
sibyl/data.py
sibyl/db/__init__.py
sibyl/db/base.py
sibyl/db/explorer.py
sibyl/db/output_presets.yml
sibyl/db/preprocessing.py
sibyl/db/schema.py
sibyl/db/utils.py
sibyl/helpers.py
sibyl/resources/__init__.py
sibyl/resources/computing.py
sibyl/resources/context.py
sibyl/resources/entity.py
sibyl/resources/feature.py
sibyl/resources/group.py
sibyl/resources/logger.py
sibyl/resources/model.py
sibyl/routes.py
sibyl/sample_applications/__init__.py
sibyl/sample_applications/housing/__init__.py
sibyl/sample_applications/housing/context_config.yml
sibyl/sample_applications/housing/features.csv
sibyl/sample_applications/housing/prepare_db.py
sibyl/sample_applications/housing/prepare_db_config.yml
sibyl/setup_wizard/__init__.py
sibyl/setup_wizard/main.py
sibyl/swagger.py
sibyl/templates/context_config_template.yml
sibyl/templates/prepare_db_config_template.yml
sibyl/utils.py
sibyl_api-0.1.2.dist-info/LICENSE
sibyl_api-0.1.2.dist-info/METADATA
sibyl_api-0.1.2.dist-info/WHEEL
sibyl_api-0.1.2.dist-info/entry_points.txt
sibyl_api-0.1.2.dist-info/RECORD
