Metadata-Version: 2.1
Name: sibyl-api
Version: 0.1.2
Summary: Explanation tool for machine learning
Home-page: https://github.com/DAI-Lab/sibyl-api
License: MIT
Keywords: sibyl-api,sibyl,api
Author: MIT Data To AI Lab
Requires-Python: >=3.9, !=2.7.*, !=3.0.*, !=3.1.*, !=3.2.*, !=3.3.*, !=3.4.*, !=3.5.*, !=3.6.*, !=3.7.*, !=3.8.*
Classifier: Development Status :: 2 - Pre-Alpha
Classifier: Intended Audience :: Developers
Classifier: License :: OSI Approved :: MIT License
Classifier: Natural Language :: English
Classifier: Programming Language :: Python :: 3
Classifier: Programming Language :: Python :: 3.9
Classifier: Programming Language :: Python :: 3.10
Classifier: Programming Language :: Python :: 3.11
Classifier: Programming Language :: Python :: 3
Classifier: Programming Language :: Python :: 3.10
Classifier: Programming Language :: Python :: 3.8
Classifier: Programming Language :: Python :: 3.9
Provides-Extra: setup
Requires-Dist: Flask (==2.2.2)
Requires-Dist: Flask-Cors (==3.0.10)
Requires-Dist: Flask-RESTful (==0.3.9)
Requires-Dist: Werkzeug (==2.2.2)
Requires-Dist: click (>=8.1.3,<9.0.0)
Requires-Dist: flasgger (==0.9.5)
Requires-Dist: gevent (>=23.9.0.post1,<24.0.0)
Requires-Dist: greenlet (>=2.0.2,<3.0.0)
Requires-Dist: mongoengine (>=0.24.2,<0.25.0)
Requires-Dist: numpy (>=1.23.3,<2.0.0)
Requires-Dist: pandas (>=1.5.0,<2.0.0)
Requires-Dist: passlib (>=1.7.4,<2.0.0)
Requires-Dist: pymongo (>=4.2.0,<5.0.0)
Requires-Dist: pyreal (>=0.4.7,<0.5.0)
Requires-Dist: pyyaml (>=6.0,<7.0)
Requires-Dist: ruamel-yaml (>=0.18.5,<0.19.0) ; extra == "setup"
Requires-Dist: streamlit (>=1.29.0,<2.0.0) ; extra == "setup"
Requires-Dist: termcolor (>=2.0.1,<3.0.0)
Requires-Dist: tqdm (>=4.66.1,<5.0.0)
Project-URL: Repository, https://github.com/DAI-Lab/sibyl-api
